bsy_clippy/__init__.py
bsy_clippy/cli.py
bsy_clippy/data/bsy-clippy.txt
bsy_clippy/data/bsy-clippy.yaml
bsy_clippy-0.3.2.dist-info/licenses/LICENSE
bsy_clippy-0.3.2.dist-info/METADATA
bsy_clippy-0.3.2.dist-info/WHEEL
bsy_clippy-0.3.2.dist-info/entry_points.txt
bsy_clippy-0.3.2.dist-info/top_level.txt
bsy_clippy-0.3.2.dist-info/RECORD
