Metadata-Version: 2.4
Name: bsy-clippy
Version: 0.3.2
Summary: Terminal client for OpenAI chat completions
Author: Sebastian Garcia
Requires-Python: >=3.8
License-File: LICENSE
Requires-Dist: openai>=1.16.0
Requires-Dist: PyYAML>=6.0
Requires-Dist: python-dotenv>=1.0
Requires-Dist: requests<3,>=2.28
Dynamic: license-file
